setup.py
AllAttachmentsMacro.egg-info/PKG-INFO
AllAttachmentsMacro.egg-info/SOURCES.txt
AllAttachmentsMacro.egg-info/dependency_links.txt
AllAttachmentsMacro.egg-info/entry_points.txt
AllAttachmentsMacro.egg-info/not-zip-safe
AllAttachmentsMacro.egg-info/top_level.txt
allattachments/__init__.py
allattachments/api.py