Metadata-Version: 1.0
Name: AllAttachmentsMacro
Version: 0.1
Summary: A Trac wiki macro that shows all attachments uploaded on a Trac site.
Home-page: UNKNOWN
Author: Daan van Etten
Author-email: daan@stuq.nl
License: CC-BY-NC-SA
Keywords: trac plugin
Platform: UNKNOWN
